watchdogs/__init__.py
watchdogs/__main__.py
watchdogs/app.py
watchdogs/background.py
watchdogs/callbacks.py
watchdogs/config.py
watchdogs/crawler.py
watchdogs/main.py
watchdogs/models.py
watchdogs/settings.py
watchdogs/utils.py
watchdogs/static/css/index.css
watchdogs/static/css/watchdogs.css
watchdogs/static/css/watchdogs.min.css
watchdogs/static/css/fonts/element-icons.woff
watchdogs/static/img/favicon.svg
watchdogs/static/js/clipboard.min.js
watchdogs/static/js/index.js
watchdogs/static/js/vue-resource.min.js
watchdogs/static/js/vue.min.js
watchdogs/static/js/watchdogs.js
watchdogs/static/js/watchdogs.min.js
watchdogs/templates/auth.html
watchdogs/templates/feeds.html
watchdogs/templates/groups.html
watchdogs/templates/index.html
watchdogs/templates/lite.html
watchdogs/templates/logs.html
watchdogs-2.0.1.dist-info/LICENSE
watchdogs-2.0.1.dist-info/METADATA
watchdogs-2.0.1.dist-info/WHEEL
watchdogs-2.0.1.dist-info/top_level.txt
watchdogs-2.0.1.dist-info/RECORD
