Metadata-Version: 2.1
Name: watchdogs
Version: 2.0.1
Summary: Watchdogs to keep an eye on the world's change. Read more: https://github.com/ClericPy/watchdogs.
Home-page: https://github.com/ClericPy/watchdogs
Author: ClericPy
Author-email: clericpy@gmail.com
License: MIT License
Keywords: requests crawler uniparser torequests fastapi watchdog
Platform: any
Classifier: License :: OSI Approved :: MIT License
Classifier: Programming Language :: Python
Classifier: Programming Language :: Python :: 3
Classifier: Programming Language :: Python :: 3.6
Classifier: Programming Language :: Python :: 3.7
Classifier: Programming Language :: Python :: 3.8
License-File: LICENSE
Requires-Dist: aiofiles
Requires-Dist: async-lru
Requires-Dist: beautifulsoup4
Requires-Dist: SQLAlchemy ==1.4.41
Requires-Dist: databases >=0.5.5
Requires-Dist: pydantic <2.0.0
Requires-Dist: fastapi
Requires-Dist: fire
Requires-Dist: jinja2
Requires-Dist: jmespath
Requires-Dist: jsonpath-rw-ext
Requires-Dist: lxml
Requires-Dist: objectpath
Requires-Dist: pyyaml >=5.3
Requires-Dist: selectolax
Requires-Dist: toml
Requires-Dist: torequests >=5.0.4
Requires-Dist: uniparser >=3.0.2
Requires-Dist: uvicorn
Requires-Dist: aiosqlite
Provides-Extra: mysql
Requires-Dist: aiomysql ; extra == 'mysql'
Requires-Dist: pymysql ; extra == 'mysql'
Provides-Extra: postgresql
Requires-Dist: asyncpg ; extra == 'postgresql'
Requires-Dist: psycopg2-binary ; extra == 'postgresql'
Provides-Extra: sqlite
Requires-Dist: aiosqlite ; extra == 'sqlite'
